{"product":{"title":"Zvučnik Bluetooth WM-1100 MP3/Usb/SD Zvucnik Card NOVO","body_html":"<p><em><span>Artikal 0447</span></em></p>\n<p> </p><em>Zvučnik Bluetooth WM-1100 MP3/Usb/SD Card NOVO</em>\n<br>\n<strong><strong><em>NOVO NEKORIŠĆENO Orginalno fabricko pakovanje, </em></strong><em>&nbsp;</em><br></strong>\n<br> \n<ul> \n <li>Kvalitetne izrade i lako prenosiv zvuznik koji se povezuje putem bluetooth-a</li> \n <li>Na telefon se moze povezati ili bezicno putem bluetooth-a ili putem USB kabla</li> \n <li>Cita&nbsp; &nbsp; &nbsp;&nbsp;<strong>microSD kartice</strong>, &nbsp; &nbsp; &nbsp;&nbsp;<strong>poseduje USB ulaz</strong>&nbsp; i ima<strong>&nbsp; FM prijemnik, &nbsp; &nbsp; &nbsp;&nbsp;</strong>moze da procita i pusa MP3 muziku sa microSD i sa USB-a. </li> \n <li>Jako kvalitetna konekcija i do 10m udaljenosti od bluetooth-a</li> \n <li>Napajanje je putem integrisane LI-ON baterije koja se puni putem USB kabla koji se dobija u paketu. </li> \n <li>Bluetooth zvucnik mozete puniti preko bilo kog usb punjaca ( upaljac za auto, kucni punjac itd. &nbsp;</li> \n <li>Postoje komande u vidu dugmica na samom bluetooth zvucniku, za kontrolu jacine zvuka kao za prebacivanje pesama sa jedne na drugu. </li> \n <li>Uredjaj moze da posluzi i da razgovarate telefonom, posto je putem bluetootha povezan na telefon a poseduje i mikrofon. </li> \n <li>Zvucnik je jacine 2x5w</li> \n</ul> \n<br> \n<p>Opis u izradi pitajte za sve što Vas zanima<br></p>\n<p>Pošaljite poruku  sa Vašim podacima:</p>\n<p><strong>Ime i prezime.                                                       </strong><br><strong>Ulica i broj.                                                       </strong><br><strong>Mesto i poštanski broj.                                                       </strong><br><strong>Broj telefona za kontakt.                             ili sms na broj 061 63 66 254</strong></p>\n<br> <br>","vendor":"061 63 66 254 minutshop.com","product_type":"Zvučnik","images":[{"alt":"Zvučnik Bluetooth WM-1100 MP3/Usb/SD Zvucnik Card NOVO","src":"https://images.kupujemprodajem.com//photos/oglasi/3/05/46168053/46168053_5914b585ac1c02-2911460720170511_203405.jpg"},{"alt":"Zvučnik Bluetooth WM-1100 MP3/Usb/SD Zvucnik Card NOVO","src":"https://images.kupujemprodajem.com//photos/oglasi/3/05/46168053/46168053_5914b584664b61-1313356320170511_203117.jpg"},{"alt":"Zvučnik Bluetooth WM-1100 MP3/Usb/SD Zvucnik Card NOVO","src":"https://images.kupujemprodajem.com//photos/oglasi/3/05/46168053/46168053_5914b584a0b5a5-7795920520170511_203125.jpg"},{"alt":"Zvučnik Bluetooth WM-1100 MP3/Usb/SD Zvucnik Card NOVO","src":"https://images.kupujemprodajem.com//photos/oglasi/3/05/46168053/46168053_5914b584e34d76-7566997520170511_203133.jpg"},{"alt":"Zvučnik Bluetooth WM-1100 MP3/Usb/SD Zvucnik Card NOVO","src":"https://images.kupujemprodajem.com//photos/oglasi/3/05/46168053/46168053_5914b58529f439-8698885320170511_203147.jpg"},{"alt":"Zvučnik Bluetooth WM-1100 MP3/Usb/SD Zvucnik Card NOVO","src":"https://images.kupujemprodajem.com//photos/oglasi/3/05/46168053/46168053_5914b5856769a4-2583959520170511_203206.jpg"},{"alt":"Zvučnik Bluetooth WM-1100 MP3/Usb/SD Zvucnik Card NOVO","src":"https://images.kupujemprodajem.com//photos/oglasi/3/05/46168053/46168053_5914b585e54c72-6701979120170511_203424.jpg"},{"alt":"Zvučnik Bluetooth WM-1100 MP3/Usb/SD Zvucnik Card NOVO","src":"https://images.kupujemprodajem.com//photos/oglasi/3/05/46168053/46168053_5914b5862e4fe5-4198530920170511_203433.jpg"},{"alt":"Zvučnik Bluetooth WM-1100 MP3/Usb/SD Zvucnik Card NOVO","src":"https://images.kupujemprodajem.com//photos/oglasi/3/05/46168053/46168053_5914b5866a4d59-9793116220170511_203508.jpg"}],"published":false,"tags":["Zvu","nik","Bluetooth","WM","1100","MP3","Usb","SD","Zvucnik","Card","NOVOAudio","Zvu","nici","","","Bluetooth","zvu","nici"],"variants":[{"price":3600,"currency_code":"RSD"}]}}